modelskill/__init__.py
modelskill/comparison/__init__.py
modelskill/comparison/_collection.py
modelskill/comparison/_collection_plotter.py
modelskill/comparison/_comparer_plotter.py
modelskill/comparison/_comparison.py
modelskill/comparison/_utils.py
modelskill/configuration.py
modelskill/data/__init__.py
modelskill/data/oresund.msk
modelskill/data/vistula.msk
modelskill/matching.py
modelskill/metrics.py
modelskill/model/__init__.py
modelskill/model/_base.py
modelskill/model/dfsu.py
modelskill/model/dummy.py
modelskill/model/factory.py
modelskill/model/grid.py
modelskill/model/point.py
modelskill/model/track.py
modelskill/obs.py
modelskill/plotting/__init__.py
modelskill/plotting/_misc.py
modelskill/plotting/_scatter.py
modelskill/plotting/_settings.py
modelskill/plotting/_spatial_overview.py
modelskill/plotting/_taylor_diagram.py
modelskill/plotting/_taylor_diagram_external.py
modelskill/plotting/_temporal_coverage.py
modelskill/plotting/_wind_rose.py
modelskill/py.typed
modelskill/quantity.py
modelskill/settings.py
modelskill/skill.py
modelskill/skill_grid.py
modelskill/styles/mood.yml
modelskill/styles/simple.yml
modelskill/timeseries/__init__.py
modelskill/timeseries/_plotter.py
modelskill/timeseries/_point.py
modelskill/timeseries/_timeseries.py
modelskill/timeseries/_track.py
modelskill/types.py
modelskill/utils.py
modelskill-1.3.0.dist-info/WHEEL
modelskill-1.3.0.dist-info/METADATA
modelskill-1.3.0.dist-info/RECORD
