Metadata-Version: 2.4
Name: modelskill
Version: 1.3.0
Summary: Compare results from simulations with observations.
Author: Jesper Sandvig Mariegaard, Henrik Andersson
Author-email: Jesper Sandvig Mariegaard <jem@dhigroup.com>, Henrik Andersson <jan@dhigroup.com>
License-Expression: MIT
Classifier: License :: OSI Approved :: MIT License
Classifier: Development Status :: 5 - Production/Stable
Classifier: Intended Audience :: Science/Research
Classifier: Programming Language :: Python
Classifier: Programming Language :: Python :: 3
Classifier: Programming Language :: Python :: 3.10
Classifier: Programming Language :: Python :: 3.11
Classifier: Programming Language :: Python :: 3.12
Classifier: Programming Language :: Python :: 3.13
Classifier: Topic :: Scientific/Engineering
Requires-Dist: numpy>1.24.4
Requires-Dist: pandas>=1.4
Requires-Dist: mikeio>=1.2
Requires-Dist: matplotlib
Requires-Dist: xarray
Requires-Dist: netcdf4
Requires-Dist: scipy
Requires-Dist: jinja2
Requires-Python: >=3.10
Project-URL: Bug Tracker, https://github.com/DHI/modelskill/issues
Project-URL: Homepage, https://github.com/DHI/modelskill
